spatk/__init__.py
spatk/circuit.py
spatk/genelems.py
spatk/helpers.py
spatk/flavours/generic.py
spatk/flavours/hspice.py
spatk/flavours/ngspice.py
spatk/flavours/xyce.py
spatk-1.5.0.dist-info/licenses/LICENSE
spatk-1.5.0.dist-info/METADATA
spatk-1.5.0.dist-info/WHEEL
spatk-1.5.0.dist-info/top_level.txt
spatk-1.5.0.dist-info/RECORD
