Metadata-Version: 2.4
Name: spatk
Version: 1.5.0
Summary: Module for handling and analyzing spice netlists
Author: Christoph Weiser
License:                     GNU GENERAL PUBLIC LICENSE
Project-URL: Homepage, https://github.com/christoph-weiser/spatk
Keywords: spice,analysis,parsing
Classifier: License :: OSI Approved :: GNU General Public License v3 or later (GPLv3+)
Classifier: Programming Language :: Python
Classifier: Programming Language :: Python :: 3
Requires-Python: >=3.9
License-File: LICENSE
Provides-Extra: dev
Requires-Dist: pytest; extra == "dev"
Dynamic: license-file
